app/__init__.py
app/core/__init__.py
app/core/invkinematics.py
app/ui/__init__.py
app/ui/main_window.py
app/ui/creators/__init__.py
app/ui/creators/project_creator.py
app/ui/creators/scene_creator.py
app/ui/creators/sprite_creator.py
app/ui/editor/__init__.py
app/ui/editor/project_editor.py
app/widgets/__init__.py
app/widgets/main/__init__.py
app/widgets/main/frame_visualiser.py
app/widgets/main/point_visualiser.py
app/widgets/main/video_animation.py
app/widgets/misc/__init__.py
app/widgets/misc/menu_bar.py
app/widgets/misc/render_config_edit.py
app/widgets/misc/render_worker.py
app/widgets/misc/video_player.py
flapkine-1.0.0.dist-info/licenses/LICENSE
src/__init__.py
src/version.py
src/blender/__init__.py
src/blender/create_frames.py
src/core/__init__.py
src/core/core.py
src/core/inverse_kinematics/__init__.py
src/core/inverse_kinematics/analytical_methods.py
src/core/transforms/__init__.py
src/core/transforms/euler_angles.py
src/core/transforms/flexibility.py
src/core/transforms/functional_flexibility.py
src/core/transforms/rotation.py
src/core/transforms/translation.py
src/core/transforms/vtk_transform.py
src/utils/__init__.py
src/utils/utils.py
flapkine-1.0.0.dist-info/METADATA
flapkine-1.0.0.dist-info/WHEEL
flapkine-1.0.0.dist-info/entry_points.txt
flapkine-1.0.0.dist-info/top_level.txt
flapkine-1.0.0.dist-info/RECORD
