Metadata-Version: 2.4
Name: FlapKine
Version: 1.0.0
Summary: A Simulation Toolkit for the Kinematics of Flapping-Wing Micro Aerial Vehicles
Author: Kalbhavi Vadhiraj
Author-email: raj.31@iitj.ac.in
Classifier: Programming Language :: Python :: 3
Classifier: Topic :: Scientific/Engineering :: Visualization
Requires-Python: <3.12
License-File: LICENSE
Requires-Dist: pandas==2.0.2
Requires-Dist: numpy==1.26.4
Requires-Dist: numpy-stl==3.1.1
Requires-Dist: scipy==1.10.1
Requires-Dist: scikit-learn==1.5.2
Requires-Dist: PyQt5==5.15.9
Requires-Dist: QtAwesome==1.4.0
Requires-Dist: vtk==9.4.1
Requires-Dist: opencv-python-headless==4.10.0.84
Provides-Extra: test
Requires-Dist: pytest>=8.3.0; extra == "test"
Requires-Dist: pytest-qt>=4.4.0; extra == "test"
Requires-Dist: pytest-mock>=3.14.0; extra == "test"
Dynamic: author
Dynamic: author-email
Dynamic: classifier
Dynamic: description
Dynamic: description-content-type
Dynamic: license-file
Dynamic: provides-extra
Dynamic: requires-dist
Dynamic: requires-python
Dynamic: summary
